{"noiseKey":{"private":{"type":"Buffer","data":"aIvDmhH51DcPCOvxictaAN0GvpHsdlSluuDOACc64X0="},"public":{"type":"Buffer","data":"C6DCxv8LG4R9YN3ujGfD6B41QPptlaN3l7tYGBdYPSQ="}},"pairingEphemeralKeyPair":{"private":{"type":"Buffer","data":"MOQuFDWrAvQ+j45x3SMwmXzA4kaFOG2BKL5oO20mw0k="},"public":{"type":"Buffer","data":"yayPgKn0NdJLDJfDYwG/xs6zRTC0mwynUn6WaSKvSh4="}},"signedIdentityKey":{"private":{"type":"Buffer","data":"kANA0aT5C7pv+Qw4jX4FzaAfFWXHYeEfaMDy2XMJTGc="},"public":{"type":"Buffer","data":"DrrFnd5G5Z75+ORRia5xsE+7K1+gqIBGG97eh9g8dXo="}},"signedPreKey":{"keyPair":{"private":{"type":"Buffer","data":"ACIhm2J4mYxSRtjVO082zDbF9LTSwZloG/8wDyXgSk8="},"public":{"type":"Buffer","data":"YR5H39LW/gShJaGF2XlGLE90LmU7Ha/Kkf/WGm/yVWo="}},"signature":{"type":"Buffer","data":"2ElB4ic4+9rmoE5Utkm3VANmtgAMBF1z+PLtjft4nQAP3IXg/xkAf9bKr1HUbcCPrcYrDHOEMiORXyE1YY9cCA=="},"keyId":1},"registrationId":82,"advSecretKey":"vtflvt1ECnmmZ1OmcaoZb2jxZg0E7dgfsYziMKrjIyk=","processedHistoryMessages":[{"key":{"remoteJid":"5511983283363@s.whatsapp.net","fromMe":false,"id":"ACD1F02C3C75999F8F8794A7F259C866","participant":"","addressingMode":"pn"},"messageTimestamp":1772135573},{"key":{"remoteJid":"5511983283363@s.whatsapp.net","fromMe":false,"id":"AC60631C80AFB1DEAF200B0AD50D1E80","participant":"","addressingMode":"pn"},"messageTimestamp":1772135573},{"key":{"remoteJid":"5511983283363@s.whatsapp.net","fromMe":false,"id":"ACB53D3D5ACEBB8708765BD2BA325045","participant":"","addressingMode":"pn"},"messageTimestamp":1772135574},{"key":{"remoteJid":"5511983283363@s.whatsapp.net","fromMe":false,"id":"AC75DF1B29D8A56E4DC65A90BEEEC556","participant":"","addressingMode":"pn"},"messageTimestamp":1772135574},{"key":{"remoteJid":"5511983283363@s.whatsapp.net","fromMe":false,"id":"ACCFB5FEAABC76CA91B4899F1DD30310","participant":"","addressingMode":"pn"},"messageTimestamp":1772135580},{"key":{"remoteJid":"5511983283363@s.whatsapp.net","fromMe":false,"id":"ACA39ED37D0FE9921CD59E193CA15119","participant":"","addressingMode":"pn"},"messageTimestamp":1772135584},{"key":{"remoteJid":"5511983283363@s.whatsapp.net","fromMe":false,"id":"AC05E288D8CA171D958A39FBF48E7465","participant":"","addressingMode":"pn"},"messageTimestamp":1772135587},{"key":{"remoteJid":"5511983283363@s.whatsapp.net","fromMe":false,"id":"AC9E050ABD724D83E86A3CEB633E6716","participant":"","addressingMode":"pn"},"messageTimestamp":1772135591},{"key":{"remoteJid":"5511983283363@s.whatsapp.net","fromMe":false,"id":"ACC00A4D87468DC77A274A5C7695FDD4","participant":"","addressingMode":"pn"},"messageTimestamp":1772135595},{"key":{"remoteJid":"5511983283363@s.whatsapp.net","fromMe":false,"id":"ACB00A0C673665C04CB53BAC67940484","participant":"","addressingMode":"pn"},"messageTimestamp":1772135598},{"key":{"remoteJid":"5511983283363@s.whatsapp.net","fromMe":false,"id":"AC1AE7898D370D72EE53AD43D404539E","participant":"","addressingMode":"pn"},"messageTimestamp":1772135601},{"key":{"remoteJid":"5511983283363@s.whatsapp.net","fromMe":false,"id":"ACA883FF900F72957378C30B54E122AF","participant":"","addressingMode":"pn"},"messageTimestamp":1772135605},{"key":{"remoteJid":"5511983283363@s.whatsapp.net","fromMe":false,"id":"ACF448D15C6CD47A522EE0E117DB6415","participant":"","addressingMode":"pn"},"messageTimestamp":1772135665},{"key":{"remoteJid":"5511983283363@s.whatsapp.net","fromMe":false,"id":"ACB3EF5E44AA02709CA4CDB7068CC386","participant":"","addressingMode":"pn"},"messageTimestamp":1772135679},{"key":{"remoteJid":"5511983283363@s.whatsapp.net","fromMe":false,"id":"ACAF98A846685E895F950E2D25DF652B","participant":"","addressingMode":"pn"},"messageTimestamp":1772135695},{"key":{"remoteJid":"5511983283363@s.whatsapp.net","fromMe":false,"id":"ACBA7A3E416E95073E52E805DC5B4BC0","participant":"","addressingMode":"pn"},"messageTimestamp":1772135709},{"key":{"remoteJid":"5511983283363@s.whatsapp.net","fromMe":false,"id":"ACCC28392C2B1B57DDF1B76E38773094","participant":"","addressingMode":"pn"},"messageTimestamp":1772135724},{"key":{"remoteJid":"5511983283363@s.whatsapp.net","fromMe":false,"id":"ACE44B918CC08C2D86053173344F75AB","participant":"","addressingMode":"pn"},"messageTimestamp":1772135737},{"key":{"remoteJid":"5511983283363@s.whatsapp.net","fromMe":false,"id":"ACFFC9DF74B1501F3C875B15A8F31549","participant":"","addressingMode":"pn"},"messageTimestamp":1772135752},{"key":{"remoteJid":"5511983283363@s.whatsapp.net","fromMe":false,"id":"ACECBD48D1436BA203ECB78A1EF58FCB","participant":"","addressingMode":"pn"},"messageTimestamp":1772135767},{"key":{"remoteJid":"5511983283363@s.whatsapp.net","fromMe":false,"id":"AC425394DB8E8569D63609F3B1BE4D0F","participant":"","addressingMode":"pn"},"messageTimestamp":1772135780},{"key":{"remoteJid":"5511983283363@s.whatsapp.net","fromMe":false,"id":"ACA27B44E82F14EFB6F9E2C792023301","participant":"","addressingMode":"pn"},"messageTimestamp":1772135794},{"key":{"remoteJid":"5511983283363@s.whatsapp.net","fromMe":false,"id":"AC647841F38564AAD6BF4EF533EE5BA5","participant":"","addressingMode":"pn"},"messageTimestamp":1772135808},{"key":{"remoteJid":"5511983283363@s.whatsapp.net","fromMe":false,"id":"ACEC433EFD618F8D2368E95726B1DBDF","participant":"","addressingMode":"pn"},"messageTimestamp":1772135823},{"key":{"remoteJid":"5511983283363@s.whatsapp.net","fromMe":false,"id":"AC71CC19BE30AB276D225A360F30C7DE","participant":"","addressingMode":"pn"},"messageTimestamp":1772135837},{"key":{"remoteJid":"5511983283363@s.whatsapp.net","fromMe":false,"id":"AC678032DA3DC1A5B218DE356A3B1905","participant":"","addressingMode":"pn"},"messageTimestamp":1772135840},{"key":{"remoteJid":"5511983283363@s.whatsapp.net","fromMe":false,"id":"AC43C670FC44255022EC459DEBC64F2E","participant":"","addressingMode":"pn"},"messageTimestamp":1772135987},{"key":{"remoteJid":"5511983283363@s.whatsapp.net","fromMe":false,"id":"AC83FB5AA9E0BC41244566439F42F8A4","participant":"","addressingMode":"pn"},"messageTimestamp":1772156295},{"key":{"remoteJid":"5511983283363@s.whatsapp.net","fromMe":false,"id":"ACA2B9F2CA5830E0B565F03EE254845E","participant":"","addressingMode":"pn"},"messageTimestamp":1772156296},{"key":{"remoteJid":"5511983283363@s.whatsapp.net","fromMe":false,"id":"AC88E4FA5A880357C36BE789186AE310","participant":"","addressingMode":"pn"},"messageTimestamp":1772156299},{"key":{"remoteJid":"5511983283363@s.whatsapp.net","fromMe":false,"id":"AC86EF67C08A46F009FA9C9033FCABA0","participant":"","addressingMode":"pn"},"messageTimestamp":1772156302},{"key":{"remoteJid":"5511983283363@s.whatsapp.net","fromMe":false,"id":"AC88F5490A02207E59C4064850D8CB10","participant":"","addressingMode":"pn"},"messageTimestamp":1772156305},{"key":{"remoteJid":"5511983283363@s.whatsapp.net","fromMe":false,"id":"AC792727328C91D35146F62C6D7A505E","participant":"","addressingMode":"pn"},"messageTimestamp":1772156307},{"key":{"remoteJid":"5511983283363@s.whatsapp.net","fromMe":false,"id":"ACFD312AA5D7A194D03B03014789DDA8","participant":"","addressingMode":"pn"},"messageTimestamp":1772156311},{"key":{"remoteJid":"5511983283363@s.whatsapp.net","fromMe":false,"id":"AC633B68BABA2D34D7B7BB75A3AED0B6","participant":"","addressingMode":"pn"},"messageTimestamp":1772156314},{"key":{"remoteJid":"5511983283363@s.whatsapp.net","fromMe":false,"id":"AC2E672358653B04DB50C8266DDDDAF1","participant":"","addressingMode":"pn"},"messageTimestamp":1772156317},{"key":{"remoteJid":"5511983283363@s.whatsapp.net","fromMe":false,"id":"ACC31E566BCBC1A1D9838E844986363E","participant":"","addressingMode":"pn"},"messageTimestamp":1772156322},{"key":{"remoteJid":"5511983283363@s.whatsapp.net","fromMe":false,"id":"ACCFE7F4D885E097DE040ADB7C6DCC82","participant":"","addressingMode":"pn"},"messageTimestamp":1772156325},{"key":{"remoteJid":"5511983283363@s.whatsapp.net","fromMe":false,"id":"AC5DE470D1A99D2BE5A45342AE8C103E","participant":"","addressingMode":"pn"},"messageTimestamp":1772156329},{"key":{"remoteJid":"5511983283363@s.whatsapp.net","fromMe":false,"id":"AC80F4C45F12405CBE6EA0BB4A5F8934","participant":"","addressingMode":"pn"},"messageTimestamp":1772156332},{"key":{"remoteJid":"5511983283363@s.whatsapp.net","fromMe":false,"id":"ACD4FE0FF0DEC3F7763B297F2B86D58A","participant":"","addressingMode":"pn"},"messageTimestamp":1772156335},{"key":{"remoteJid":"5511983283363@s.whatsapp.net","fromMe":false,"id":"ACB2D98437E7935CED37ED1239EA46AE","participant":"","addressingMode":"pn"},"messageTimestamp":1772156339}],"nextPreKeyId":1665,"firstUnuploadedPreKeyId":1665,"accountSyncCounter":1,"accountSettings":{"unarchiveChats":false},"registered":false,"account":{"details":"CI7V6OwCEIjJgs0GGB0gACgA","accountSignatureKey":"/PRKtKiBskzDrXjZLxPK96Ug0bU+H2h+wxNYIkpPC2Y=","accountSignature":"APGFEz+rnF8wQrBeWDS31woq7K2FMX/ohuzUPPxoSf7pXatG3SVb1D4bknTAqhPlVjPLgaybGYwXjhQ0/4kQCw==","deviceSignature":"6HibWN7YCUURmc2VViwjINX9kMrcjnXxUw+i9orZ/0+1mDp7kQX7HqjWadAsABmedC7AypZP8z4EFNTg4P4hCQ=="},"me":{"id":"5511983283363:68@s.whatsapp.net","lid":"175771620519938:68@lid","name":"Vicente Zip"},"signalIdentities":[{"identifier":{"name":"175771620519938:68@lid","deviceId":0},"identifierKey":{"type":"Buffer","data":"Bfz0SrSogbJMw6142S8TyvelING1Ph9ofsMTWCJKTwtm"}}],"platform":"android","routingInfo":{"type":"Buffer","data":"CBIIBQgN"},"lastAccountSyncTimestamp":1774287253,"lastPropHash":"1K4hH4","myAppStateKeyId":"AAAAAHn2"}